setup.py
distributions_GB/Binomialdistribution.py
distributions_GB/Gaussiandistribution.py
distributions_GB/Generaldistribution.py
distributions_GB/__init__.py
distributions_GB.egg-info/PKG-INFO
distributions_GB.egg-info/SOURCES.txt
distributions_GB.egg-info/dependency_links.txt
distributions_GB.egg-info/not-zip-safe
distributions_GB.egg-info/top_level.txt